<entries>
<entry name="QUEST_24_DESC">Atiende a {0} clientes en la frutería.</entry>
<entry name="QUEST_54_DESC">Mejora tu concesionario a nivel {0}.</entry>
<entry name="QUEST_59_DESC">Mejora tu joyería a nivel {0}.</entry>
<entry name="QUEST_84">¡Por la gloria!</entry>
<entry name="QUEST_94">Fruta estelar 2.0</entry>
<entry name="QUEST_24">Exporta frutas</entry>
<entry name="QUEST_34">Bip bip</entry>
<entry name="QUEST_14">¡Qué espacioso!</entry>
<entry name="QUEST_50_DESC">Mejora tu perfumería a nivel {0}.</entry>
<entry name="QUEST_38_DESC">Construye un nuevo supermercado en Beverly Hills.</entry>
<entry name="QUEST_44">Esto tiene una pinta rara</entry>
<entry name="QUEST_54">Potencia</entry>
<entry name="QUEST_101_DESC">Consigue 1 estrella en tu tienda de moda</entry>
<entry name="QUEST_59">Bonito y protector</entry>
<entry name="QUEST_74_DESC">Construye un nuevo supermercado en Tokyo.</entry>
<entry name="QUEST_79_DESC">Mejora tu pescadería a nivel {0}.</entry>
<entry name="QUEST_18">Adiós a los dulces</entry>
<entry name="QUEST_76_DESC">Mejora tu tienda de smartphones a nivel {0}.</entry>
<entry name="QUEST_70_DESC">Mejora tu inmobiliaria a nivel {0}.</entry>
<entry name="QUEST_14_DESC">Mejora tu parking a nivel {0}.</entry>
<entry name="QUEST_19_DESC">Construye una pescadería en tu supermercado.</entry>
<entry name="QUEST_104">Fruta estelar 3.0</entry>
<entry name="QUEST_82">E=mc²</entry>
<entry name="QUEST_39_DESC">Construye una joyería en tu supermercado.</entry>
<entry name="QUEST_62_DESC">Construye una inmobiliaria en tu supermercado.</entry>
<entry name="QUEST_10_DESC">Mejora tu frutería a nivel {0}.</entry>
<entry name="QUEST_82_DESC">Mejora tu joyería a nivel {0}.</entry>
<entry name="QUEST_63_DESC">Mejora tu inmobiliaria a nivel {0}.</entry>
<entry name="QUEST_36_DESC">Construye una tienda de smartphones en tu supermercado.</entry>
<entry name="QUEST_83_DESC">Mejora tu inmobiliaria a nivel {0}.</entry>
<entry name="QUEST_2_DESC">Atiende a {0} clientes en la frutería.</entry>
<entry name="QUEST_34_DESC">Construye una tienda de electrónica en tu supermercado.</entry>
<entry name="QUEST_56_DESC">Mejora tu frutería a nivel {0}.</entry>
<entry name="QUEST_57_DESC">Mejora tu panadería a nivel {0}.</entry>
<entry name="QUEST_8_DESC">Mejora tu parking a nivel {0}.</entry>
<entry name="QUEST_30_DESC">Mejora tu perfumería a nivel {0}.</entry>
<entry name="QUEST_92">Primeros colonos</entry>
<entry name="QUEST_98">Interestelar</entry>
<entry name="QUEST_71_DESC">Mejora tu panadería a nivel {0}.</entry>
<entry name="QUEST_33">¡Sí! playa</entry>
<entry name="QUEST_22_DESC">Atiende a {0} clientes en la pescadería.</entry>
<entry name="QUEST_108">carne estelar 3.0</entry>
<entry name="QUEST_1_DESC">Mejora tu frutería a nivel {0}.</entry>
<entry name="QUEST_77_DESC">Mejora tu concesionario a nivel {0}.</entry>
<entry name="QUEST_23_DESC">Construye una tienda de moda en tu supermercado.</entry>
<entry name="QUEST_11_DESC">Atiende a {0} clientes en la frutería.</entry>
<entry name="QUEST_16_DESC">Mejora tu carnicería a nivel {0}.</entry>
<entry name="QUEST_17_DESC">Mejora tu panadería a nivel {0}.</entry>
<entry name="QUEST_36">¿Dígame?</entry>
<entry name="QUEST_25">Viste bien</entry>
<entry name="QUEST_106_DESC">Mejora tu inmobiliaria a nivel {0}.</entry>
<entry name="QUEST_85">Fruta estelar</entry>
<entry name="QUEST_95">Divino</entry>
<entry name="QUEST_45_DESC">Mejora tu tienda de electrónica a nivel {0}.</entry>
<entry name="QUEST_31_DESC">Atiende a {0} clientes en la perfumería.</entry>
<entry name="QUEST_28_DESC">Construye un nuevo supermercado en una pequeña ciudad</entry>
<entry name="QUEST_110_DESC">Consigue 2 estrellas en tu tienda de electrodomésticos</entry>
<entry name="QUEST_15">Viento en popa</entry>
<entry name="QUEST_65">Pulsera de superhéroe</entry>
<entry name="QUEST_37_DESC">Mejora tu tienda de smartphones a nivel {0}.</entry>
<entry name="QUEST_45">Clic Clic</entry>
<entry name="QUEST_55">El rojo siempre corre más</entry>
<entry name="QUEST_64_DESC">Mejora tu concesionario a nivel {0}.</entry>
<entry name="QUEST_69_DESC">Mejora tu concesionario a nivel {0}.</entry>
<entry name="QUEST_80">¿Qué hora es?</entry>
<entry name="QUEST_89_DESC">Mejora tu concesionario a nivel {0}.</entry>
<entry name="QUEST_92_DESC">Mejora tu inmobiliaria a nivel {0}.</entry>
<entry name="QUEST_78_DESC">Mejora tu carnicería a nivel {0}.</entry>
<entry name="QUEST_100_DESC">Consigue 2 estrellas en tu pescadería</entry>
<entry name="QUEST_20">Expansión</entry>
<entry name="QUEST_30">¡Más pasta!</entry>
<entry name="QUEST_111_DESC">Mejora tu joyería a nivel {0}.</entry>
<entry name="QUEST_60_DESC">Mejora tu concesionario a nivel {0}.</entry>
<entry name="QUEST_60">Me sobra la pasta</entry>
<entry name="QUEST_70">A tomar el sol</entry>
<entry name="QUEST_40">Para las orejas</entry>
<entry name="QUEST_50">Huele a chorizo</entry>
<entry name="QUEST_101">Moda estelar</entry>
<entry name="QUEST_93_DESC">Consigue 1 estrella en tu pescadería</entry>
<entry name="QUEST_107">Inmortal</entry>
<entry name="QUEST_106">Andrómeda</entry>
<entry name="QUEST_83">Abracadabra</entry>
<entry name="QUEST_93">Pescado estelar</entry>
<entry name="QUEST_23">Crea tendencia</entry>
<entry name="QUEST_31">En efectivo, por favor</entry>
<entry name="QUEST_13">Pedidos a tope</entry>
<entry name="QUEST_63">Con buenas vistas</entry>
<entry name="QUEST_73">No necesitas fuerza</entry>
<entry name="QUEST_43">Señor Elegante</entry>
<entry name="QUEST_53">Amor y luces</entry>
<entry name="QUEST_29_DESC">Mejora tu tienda de moda a nivel {0}.</entry>
<entry name="QUEST_98_DESC">Mejora tu concesionario a nivel {0}.</entry>
<entry name="QUEST_113_DESC">Mejora tu inmobiliaria a nivel {0}.</entry>
<entry name="QUEST_84_DESC">Mejora tu tienda de moda a nivel {0}.</entry>
<entry name="QUEST_102_DESC">Consigue 1 estrella en tu perfumería</entry>
<entry name="QUEST_20_DESC">Construye un nuevo supermercado en un pueblo pequeño.</entry>
<entry name="QUEST_61_DESC">Mejora tu pescadería a nivel {0}.</entry>
<entry name="QUEST_66_DESC">Construye un nuevo supermercado en Londres.</entry>
<entry name="QUEST_103_DESC">Consigue 1 estrella en tu tienda de electrodomésticos</entry>
<entry name="QUEST_81_DESC">Construye un nuevo supermercado en Hong Kong.</entry>
<entry name="QUEST_86_DESC">Construye un nuevo supermercado en Nueva York.</entry>
<entry name="QUEST_67_DESC">Mejora tu frutería a nivel {0}.</entry>
<entry name="QUEST_87_DESC">Consigue 1 estrella en tu panadería</entry>
<entry name="QUEST_103">electrodomésticos estelares</entry>
<entry name="QUEST_55_DESC">Mejora tu concesionario a nivel {0}.</entry>
<entry name="QUEST_7_DESC">Mejora tu panadería a nivel {0}.</entry>
<entry name="QUEST_64">Señor presidente</entry>
<entry name="QUEST_77">Nanananananana</entry>
<entry name="QUEST_105_DESC">Construye un nuevo supermercado en Marte</entry>
<entry name="QUEST_94_DESC">Consigue 2 estrellas en tu frutería</entry>
<entry name="QUEST_99_DESC">Consigue 2 estrellas en tu carnicería</entry>
<entry name="QUEST_104_DESC">Consigue 3 estrellas en tu frutería</entry>
<entry name="QUEST_86">Sueño americano</entry>
<entry name="QUEST_75_DESC">Mejora tu concesionario a nivel {0}.</entry>
<entry name="QUEST_21_DESC">Mejora tu pescadería a nivel {0}.</entry>
<entry name="QUEST_26_DESC">Recoge las ganancias de {0} camiones.</entry>
<entry name="QUEST_90_DESC">Consigue 1 estrella en tu carnicería</entry>
<entry name="QUEST_26">Cadena de transporte</entry>
<entry name="QUEST_27_DESC">Construye una perfumería en tu supermercado</entry>
<entry name="QUEST_16">Fresca y roja</entry>
<entry name="QUEST_66">Fish &amp; Chips</entry>
<entry name="QUEST_76">¿Tatarabuelo, eres tu?</entry>
<entry name="QUEST_46">Sobre ruedas</entry>
<entry name="QUEST_56">Qué rrrrrrrica</entry>
<entry name="QUEST_15_DESC">Alcanza {0} en ganancias acumuladas de por vida.</entry>
<entry name="QUEST_109_DESC">Consigue 2 estrellas en tu perfumería</entry>
<entry name="QUEST_81">Operación Dragón</entry>
<entry name="QUEST_91">Fly me to the moon</entry>
<entry name="QUEST_112_DESC">Consigue 3 estrellas en tu pescadería</entry>
<entry name="QUEST_21">Pescado de calidad</entry>
<entry name="QUEST_10">¡Que refrescante!</entry>
<entry name="QUEST_11">Clientes muy sanos</entry>
<entry name="QUEST_61">Pulpo al horno</entry>
<entry name="QUEST_71">El mejor pan</entry>
<entry name="QUEST_41">¡De colores!</entry>
<entry name="QUEST_51">Agente 000-000000-07</entry>
<entry name="QUEST_111">Gobiérnalos a todos</entry>
<entry name="QUEST_110">electrodomésticos estelares 2.0</entry>
<entry name="QUEST_35_DESC">Mejora tu tienda de electrónica a nivel {0}.</entry>
<entry name="QUEST_114">Fruta estelar 4.0</entry>
<entry name="QUEST_68_DESC">Mejora tu inmobiliaria a nivel {0}.</entry>
<entry name="QUEST_32">Fructosa</entry>
<entry name="QUEST_75">El futuro ha llegado</entry>
<entry name="QUEST_96_DESC">Mejora tu tienda de electrónica a nivel {0}.</entry>
<entry name="QUEST_97_DESC">Mejora tu inmobiliaria a nivel {0}.</entry>
<entry name="QUEST_100">Pescado estelar 2.0</entry>
<entry name="QUEST_107_DESC">Mejora tu tienda de smartphones a nivel {0}.</entry>
<entry name="QUEST_6_DESC">Mejora tu frutería a nivel {0}.</entry>
<entry name="QUEST_90">Carne estelar</entry>
<entry name="QUEST_42_DESC">Mejora tu pescadería a nivel {0}.</entry>
<entry name="QUEST_43_DESC">Mejora tu tienda de moda a nivel {0}.</entry>
<entry name="QUEST_102">fragancia estelar</entry>
<entry name="QUEST_113">Planeta entero</entry>
<entry name="QUEST_88_DESC">Mejora tu inmobiliaria a nivel {0}.</entry>
<entry name="QUEST_5_DESC">Construye una panadería en tu supermercado.</entry>
<entry name="QUEST_74">Konichiwa</entry>
<entry name="QUEST_47">El origen de todo</entry>
<entry name="QUEST_35">100101001</entry>
<entry name="QUEST_65_DESC">Mejora tu joyería a nivel {0}.</entry>
<entry name="QUEST_109">fragancia estelar 2.0</entry>
<entry name="QUEST_85_DESC">Consigue 1 estrella en tu frutería</entry>
<entry name="QUEST_97">Dos semanas</entry>
<entry name="QUEST_48_DESC">Mejora tu concesionario a nivel {0}.</entry>
<entry name="QUEST_88">Casa espacial</entry>
<entry name="QUEST_27">Aroma atractivo</entry>
<entry name="QUEST_37">Nuevo modelo</entry>
<entry name="QUEST_17">Menudo aroma</entry>
<entry name="QUEST_67">Para desayunar</entry>
<entry name="QUEST_28">Expande tu marca</entry>
<entry name="QUEST_38">Vecinos ricos</entry>
<entry name="QUEST_8">¡Bienvenidos!</entry>
<entry name="QUEST_9">Recién hecho</entry>
<entry name="QUEST_68">7 baños tiene mi casa</entry>
<entry name="QUEST_78">Pues no es tan sabrosa</entry>
<entry name="QUEST_48">&quot;Si no consume tanto&quot;</entry>
<entry name="QUEST_51_DESC">Mejora tu tienda de moda a nivel {0}.</entry>
<entry name="QUEST_2">Fruta para todos</entry>
<entry name="QUEST_3">Servicio a domicilio</entry>
<entry name="QUEST_1">Mejores productos</entry>
<entry name="QUEST_6">Fruta fresca</entry>
<entry name="QUEST_7">Pan saludable</entry>
<entry name="QUEST_4">Adelante</entry>
<entry name="QUEST_5">Mmm, que bien huele</entry>
<entry name="QUEST_12">¡Sabroso!</entry>
<entry name="QUEST_62">Bienvenido a casa</entry>
<entry name="QUEST_72">Cogidos del cielo</entry>
<entry name="QUEST_42">Dientes afilados</entry>
<entry name="QUEST_52">¿En serio?</entry>
<entry name="QUEST_108_DESC">Consigue 3 estrellas en tu carnicería</entry>
<entry name="QUEST_58">Defendamos el castillo</entry>
<entry name="QUEST_96">100800p</entry>
<entry name="QUEST_25_DESC">Atiende a {0} clientes en la tienda de moda.</entry>
<entry name="QUEST_114_DESC">Consigue 4 estrellas en tu frutería</entry>
<entry name="QUEST_44_DESC">Mejora tu frutería a nivel {0}.</entry>
<entry name="QUEST_49_DESC">Mejora tu tienda de electrónica a nivel {0}.</entry>
<entry name="QUEST_52_DESC">Recoge las ganancias de {0} camiones.</entry>
<entry name="QUEST_53_DESC">Construye un nuevo supermercado en París.</entry>
<entry name="QUEST_87">Pan estelar</entry>
<entry name="QUEST_40_DESC">Mejora tu joyería a nivel {0}.</entry>
<entry name="QUEST_80_DESC">Mejora tu concesionario a nivel {0}.</entry>
<entry name="QUEST_4_DESC">Mejora tu parking a nivel {0}.</entry>
<entry name="QUEST_72_DESC">Mejora tu joyería a nivel {0}.</entry>
<entry name="QUEST_73_DESC">Mejora tu tienda de electrónica a nivel {0}.</entry>
<entry name="QUEST_95_DESC">Mejora tu perfumería a nivel {0}.</entry>
<entry name="QUEST_58_DESC">Mejora tu tienda de moda a nivel {0}.</entry>
<entry name="QUEST_12_DESC">Construye una carnicería en tu supermercado.</entry>
<entry name="QUEST_112">Pescado estelar 3.0</entry>
<entry name="QUEST_13_DESC">Recoge las ganancias de {0} camiones.</entry>
<entry name="QUEST_22">Dieta equilibrada</entry>
<entry name="QUEST_57">Chico.... traéme ese pan</entry>
<entry name="QUEST_91_DESC">Construye un nuevo supermercado en la Luna</entry>
<entry name="QUEST_3_DESC">Recoge las ganancias de {0} camiones.</entry>
<entry name="QUEST_41_DESC">Mejora tu carnicería a nivel {0}.</entry>
<entry name="QUEST_46_DESC">Construye un concesionario en tu supermercado.</entry>
<entry name="QUEST_32_DESC">Mejora tu frutería a nivel {0}.</entry>
<entry name="QUEST_89">Coche espacial</entry>
<entry name="QUEST_105">Planeta rojo</entry>
<entry name="QUEST_47_DESC">Mejora tu panadería a nivel {0}.</entry>
<entry name="QUEST_33_DESC">Construye un nuevo supermercado en Miami.</entry>
<entry name="QUEST_99">carne estelar 2.0</entry>
<entry name="QUEST_9_DESC">Atiende a {0} clientes en la panadería.</entry>
<entry name="QUEST_29">No está mal</entry>
<entry name="QUEST_39">Reluciente</entry>
<entry name="QUEST_18_DESC">Mejora tu frutería a nivel {0}.</entry>
<entry name="QUEST_19">¡Mira que fresco!</entry>
<entry name="QUEST_69">Reluciente como el oro</entry>
<entry name="QUEST_79">¡Tritones!</entry>
<entry name="QUEST_49">Cocinero ocioso</entry>
</entries>
